{
   "0": {
      "0": [
         {
            "string": "W0A36",
            "subject": "Calculus 2",
            "classroom": "A1.08"
         }
      ],
      "1": [
         {
            "string": "P0A35",
            "subject": "Compilerbouw",
            "classroom": "A1.08"
         }
      ],
      "2": [
         {
            "string": "L1A27",
            "subject": "Data Mining",
            "classroom": "A1.08"
         }
      ],
      "3": [
         {
            "string": "W0A16",
            "subject": "Collectieve Intelligentie",
            "classroom": "A1.08"
         }
      ]
   },
   "1": {
      "0": [],
      "1": [
         {
            "string": "W0A15",
            "subject": "Bioinformatica",
            "classroom": "A1.08"
         }
      ],
      "2": [
         {
            "string": "P0A19",
            "subject": "Programmeren in Java 2",
            "classroom": "A1.08"
         }
      ],
      "3": []
   },
   "2": {
      "0": [
         {
            "string": "W0A34",
            "subject": "Calculus 2",
            "classroom": "A1.08"
         },
         {
            "string": "P0A15",
            "subject": "Project Numerical Recipes",
            "classroom": "A1.08"
         },
         {
            "string": "W0A19",
            "subject": "Webprogrammeren en databases",
            "classroom": "A1.08"
         },
         {
            "string": "P0A14",
            "subject": "Zoeken, sturen en bewegen",
            "classroom": "A1.08"
         }
      ],
      "1": [],
      "2": [
         {
            "string": "L1A25",
            "subject": "Interactie-ontwerp",
            "classroom": "A1.08"
         }
      ],
      "3": [
         {
            "string": "L0A61",
            "subject": "Collectieve Intelligentie",
            "classroom": "A1.08"
         },
         {
            "string": "W0A8",
            "subject": "Autonomous Agents 2",
            "classroom": "A1.08"
         }
      ]
   },
   "3": {
      "0": [
         {
            "string": "L0A106",
            "subject": "Calculus 2",
            "classroom": "A1.08"
         }
      ],
      "1": [],
      "2": [
         {
            "string": "L1A45",
            "subject": "Bioinformatica",
            "classroom": "A1.08"
         }
      ],
      "3": []
   },
   "4": {
      "0": [],
      "1": [
         {
            "string": "L1A84",
            "subject": "Kansrekenen 2",
            "classroom": "A1.08"
         }
      ],
      "2": [
         {
            "string": "P0A8",
            "subject": "Autonomous Agents 2",
            "classroom": "A1.08"
         },
         {
            "string": "L0A22",
            "subject": "Machine Learning",
            "classroom": "A1.08"
         },
         {
            "string": "P0A16",
            "subject": "Collectieve Intelligentie",
            "classroom": "A1.08"
         },
         {
            "string": "W0A9",
            "subject": "Data Mining",
            "classroom": "A1.08"
         }
      ],
      "3": [
         {
            "string": "L0A44",
            "subject": "Heuristieken 1",
            "classroom": "A1.08"
         },
         {
            "string": "L0A20",
            "subject": "Advanced Heuristics",
            "classroom": "A1.08"
         }
      ]
   }
}