{
   "0": {
      "0": [],
      "1": [],
      "2": [],
      "3": []
   },
   "1": {
      "0": [],
      "1": [],
      "2": [],
      "3": []
   },
   "2": {
      "0": [],
      "1": [],
      "2": [],
      "3": []
   },
   "3": {
      "0": [],
      "1": [],
      "2": [],
      "3": []
   },
   "4": {
      "0": [],
      "1": [
         {
            "subject": "Netwerken en systeembeveiliging",
            "string": "P0C16",
            "classroom": "A1.10"
         }
      ],
      "2": [],
      "3": []
   }
}