{
   "0": {
      "0": [],
      "1": [],
      "2": [],
      "3": []
   },
   "1": {
      "0": [],
      "1": [],
      "2": [],
      "3": [
         {
            "classroom": "C1.112",
            "string": "P0A12",
            "subject": "Project Genetic Algorithms"
         }
      ]
   },
   "2": {
      "0": [
         {
            "classroom": "A1.08",
            "string": "P0A15",
            "subject": "Compilerbouw (practicum)"
         }
      ],
      "1": [],
      "2": [],
      "3": []
   },
   "3": {
      "0": [],
      "1": [],
      "2": [],
      "3": [
         {
            "classroom": "A1.10",
            "string": "P0A15",
            "subject": "Zoeken, sturen en bewegen"
         }
      ]
   },
   "4": {
      "0": [],
      "1": [],
      "2": [],
      "3": []
   }
}