{
   "0": {
      "0": [
         {
            "string": "P0C20",
            "classroom": "A1.08",
            "subject": "Netwerken en systeembeveiliging"
         }
      ],
      "1": [
         {
            "string": "L0A0",
            "classroom": "C0.110",
            "subject": "Informatie- en organisatieontwerp"
         },
         {
            "string": "L0A0",
            "classroom": "A1.04",
            "subject": "Technology for games"
         }
      ],
      "2": [],
      "3": [
         {
            "string": "L0A0",
            "classroom": "A1.10",
            "subject": "Heuristieken 1"
         }
      ]
   },
   "1": {
      "0": [],
      "1": [
         {
            "string": "W0B20",
            "classroom": "B0.201",
            "subject": "Technology for games"
         }
      ],
      "2": [],
      "3": []
   },
   "2": {
      "0": [],
      "1": [
         {
            "string": "P0B10",
            "classroom": "B0.201",
            "subject": "Autonomous Agents 2"
         }
      ],
      "2": [
         {
            "string": "W0B15",
            "classroom": "A1.06",
            "subject": "Informatie- en organisatieontwerp"
         }
      ],
      "3": [
         {
            "string": "L1A0",
            "classroom": "B0.201",
            "subject": "Technology for games"
         }
      ]
   },
   "3": {
      "0": [],
      "1": [
         {
            "string": "L0A0",
            "classroom": "A1.10",
            "subject": "Autonomous Agents 2"
         },
         {
            "string": "L1A0",
            "classroom": "A1.08",
            "subject": "Autonomous Agents 2"
         }
      ],
      "2": [
         {
            "string": "W0B10",
            "classroom": "C0.110",
            "subject": "Autonomous Agents 2"
         },
         {
            "string": "P0B15",
            "classroom": "A1.10",
            "subject": "Informatie- en organisatieontwerp"
         }
      ],
      "3": [
         {
            "string": "W0A25",
            "classroom": "B0.201",
            "subject": "Heuristieken 1"
         },
         {
            "string": "L1A0",
            "classroom": "A1.04",
            "subject": "Informatie- en organisatieontwerp"
         }
      ]
   },
   "4": {
      "0": [],
      "1": [],
      "2": [],
      "3": []
   }
}