{
   "0": {
      "0": [],
      "1": [],
      "2": [
         {
            "classroom": "A1.04",
            "string": "L2A45",
            "subject": "Bioinformatica"
         }
      ],
      "3": []
   },
   "1": {
      "0": [
         {
            "classroom": "C1.112",
            "string": "W0A17",
            "subject": "Reflectie op de digitale cultuur"
         }
      ],
      "1": [
         {
            "classroom": "A1.06",
            "string": "W0A15",
            "subject": "Bioinformatica"
         }
      ],
      "2": [
         {
            "classroom": "A1.08",
            "string": "L1A45",
            "subject": "Bioinformatica"
         }
      ],
      "3": []
   },
   "2": {
      "0": [],
      "1": [],
      "2": [
         {
            "classroom": "A1.08",
            "string": "L0A45",
            "subject": "Bioinformatica"
         },
         {
            "classroom": "C1.112",
            "string": "L1A51",
            "subject": "Reflectie op de digitale cultuur"
         }
      ],
      "3": []
   },
   "3": {
      "0": [
         {
            "classroom": "A1.04",
            "string": "L0A51",
            "subject": "Reflectie op de digitale cultuur"
         }
      ],
      "1": [],
      "2": [],
      "3": []
   },
   "4": {
      "0": [
         {
            "classroom": "A1.06",
            "string": "P0A15",
            "subject": "Bioinformatica"
         }
      ],
      "1": [],
      "2": [],
      "3": []
   }
}