{
   "0": {
      "0": [],
      "1": [],
      "2": [],
      "3": []
   },
   "1": {
      "0": [],
      "1": [],
      "2": [],
      "3": []
   },
   "2": {
      "0": [],
      "1": [],
      "2": [
         {
            "classroom": "A1.06",
            "subject": "Compilerbouw (practicum)",
            "string": "P0C12"
         }
      ],
      "3": []
   },
   "3": {
      "0": [],
      "1": [],
      "2": [],
      "3": []
   },
   "4": {
      "0": [],
      "1": [],
      "2": [],
      "3": []
   }
}