{
   "0": {
      "0": [
         {
            "subject": "Calculus 2",
            "group": 0,
            "lecture_number": 0,
            "classRoom": null,
            "name": "Lecture"
         },
         {
            "subject": "Calculus 2",
            "group": 0,
            "lecture_number": 0,
            "classRoom": null,
            "name": "WorkLecture"
         }
      ],
      "1": [],
      "2": [],
      "3": []
   },
   "1": {
      "0": [],
      "1": [],
      "2": [],
      "3": []
   },
   "2": {
      "0": [],
      "1": [],
      "2": [],
      "3": []
   },
   "3": {
      "0": [],
      "1": [],
      "2": [],
      "3": []
   },
   "4": {
      "0": [],
      "1": [],
      "2": [],
      "3": []
   }
}