{
   "0": {
      "0": [],
      "1": [],
      "2": [],
      "3": [
         {
            "string": "L0A38",
            "classroom": "C1.112",
            "subject": "Technology for games"
         },
         {
            "string": "W0B19",
            "classroom": "C0.110",
            "subject": "Technology for games"
         }
      ]
   },
   "1": {
      "0": [],
      "1": [],
      "2": [],
      "3": []
   },
   "2": {
      "0": [],
      "1": [],
      "2": [
         {
            "string": "L1A84",
            "classroom": "C1.112",
            "subject": "Kansrekenen 2"
         }
      ],
      "3": []
   },
   "3": {
      "0": [],
      "1": [
         {
            "string": "L1A38",
            "classroom": "C1.112",
            "subject": "Technology for games"
         }
      ],
      "2": [],
      "3": []
   },
   "4": {
      "0": [],
      "1": [
         {
            "string": "L0A84",
            "classroom": "C1.112",
            "subject": "Kansrekenen 2"
         }
      ],
      "2": [],
      "3": []
   }
}