{
   "0": {
      "0": [],
      "1": [
         {
            "subject": "Software engineering",
            "string": "W0B37",
            "classroom": "A1.10"
         }
      ],
      "2": [],
      "3": [
         {
            "subject": "Bioinformatica",
            "string": "L0A45",
            "classroom": "A1.10"
         }
      ]
   },
   "1": {
      "0": [],
      "1": [],
      "2": [
         {
            "subject": "Bioinformatica",
            "string": "L1A45",
            "classroom": "A1.10"
         }
      ],
      "3": []
   },
   "2": {
      "0": [],
      "1": [
         {
            "subject": "Software engineering",
            "string": "L0A75",
            "classroom": "C0.110"
         }
      ],
      "2": [],
      "3": [
         {
            "subject": "Bioinformatica",
            "string": "L2A45",
            "classroom": "A1.10"
         }
      ]
   },
   "3": {
      "0": [
         {
            "subject": "Bioinformatica",
            "string": "P0B15",
            "classroom": "A1.10"
         }
      ],
      "1": [],
      "2": [],
      "3": [
         {
            "subject": "Software engineering",
            "string": "P0B37",
            "classroom": "B0.201"
         }
      ]
   },
   "4": {
      "0": [],
      "1": [],
      "2": [],
      "3": [
         {
            "subject": "Bioinformatica",
            "string": "W0B15",
            "classroom": "C0.110"
         }
      ]
   }
}